Workbook
Name ACTION: #REF!
Name ACTION: #REF!

Sheet Cover
B2: SYSTEM TEST REPORT DOCUMENT
A4: Project Name | B4: CondoCare — Apartment Building Management | E4: Team
A5: Project Code | B5: SWP391_G_CondoCare | E5: Issue Date | F5: 07/04/2026
A6: Document Code | B6: =B5&"_"&"XXX"&"_"&"vx.x" | E6: Version
A9: Record of change
A10: Effective Date | B10: Version | C10: Change Item | D10: *A,D,M | E10: Change description | F10: Reference
A11: 07/04/2026 | B11: v1.0 | C11: Initial complete system test — UC01–UC29 | D11: A | F11: CondoCare RDS v1.1

Sheet Test Cases
D1: TEST CASE LIST
B3: Project Name | D3: =#REF!
B4: Project Code | D4: CondoCare — Apartment Building Management
B5: Test Environment Setup Description | D5: SWP391_G_CondoCare
D6: 1. Java 17 + Spring Boot 3 2. MySQL 8 (SWP391 database) 3. Chrome / Firefox browser 4. MoMo Sandbox credentials configured 5. Gmail SMTP (App Password) configured
B8: 1 | C8: Authentication | D8: Workflow Authentication | E8: UC01–UC04: Register, Login, Logout, Forgot/Reset Password
B9: 2 | C9: Staff Dashboard + Profile | D9: Workflow Dashboard | E9: UC05–UC08: Profile Mgmt + Dashboard Overview
B10: 3 | C10: Staff Management | D10: Workflow Management | E10: UC09–UC12: Staff, Resident, Building, Fee Templates
B11: 4 | C11: Invoice & Payment | D11: Workflow Invoice | E11: UC13–UC17: Create/View Invoice, Update Status, Pay MoMo
B12: 5 | C12: Service Requests + Vehicles + Notifications | D12: Workflow Request | E12: UC18–UC29: Requests, Vehicles, Notifications, Apt Info
B13: 5 | C13: Function E | D13: Workflow Name2

Sheet Test Statistics
B1: TEST STATISTICS
B3: Project Name | C3: <Project Name> | E3: Creator
B4: Project Code | C4: CondoCare — Apartment Building Management | E4: Reviewer/Approver
B5: Document Code | C5: SWP391_G_CondoCare | E5: Issue Date | H5: <Date when this test report is created>
B6: Notes | C6: <List modules included in this release> ex: Release 1 includes 2 modules: Module1 and Module2
C7: Release 1.0: Authentication, Dashboard, Management, Invoice, Requests, Vehicles, Notifications
B9: 1 | C9: Workflow Authentication | D9: ='Workflow Authentication '!B6 | E9: ='Workflow Authentication '!C6 | F9: ='Workflow Authentication '!D6 | G9: ='Workflow Authentication '!E6 | H9: ='Workflow Authentication '!B4
B10: 2 | C10: Workflow Dashboard | D10: ='Workflow Dashboard'!B6 | E10: ='Workflow Dashboard'!C6 | F10: ='Workflow Dashboard'!D6 | G10: ='Workflow Dashboard'!E6 | H10: ='Workflow Dashboard'!B4
B11: 3 | C11: Workflow Management | D11: ='Workflow Management'!B6 | E11: ='Workflow Management'!C6 | F11: ='Workflow Management'!D6 | G11: ='Workflow Management'!E6 | H11: ='Workflow Management'!B4
B12: 4 | C12: Workflow Invoice | D12: ='Workflow Invoice'!B6 | E12: ='Workflow Invoice'!C6 | F12: ='Workflow Invoice'!D6 | G12: ='Workflow Invoice'!E6 | H12: ='Workflow Invoice'!B4
B13: 5 | C13: Workflow Request | D13: ='Workflow Request'!B6 | E13: ='Workflow Request'!C6 | F13: ='Workflow Request'!D6 | G13: ='Workflow Request'!E6 | H13: ='Workflow Request'!B4
C14: Sub total | D14: =SUM(D9:D13) | E14: =SUM(E9:E13) | F14: =SUM(F9:F13) | G14: =SUM(G9:G13) | H14: =SUM(H9:H13)
C16: Test coverage | E16: =(D14+E14)*100/(H14-G14) | F16: %
C17: Test successful coverage | E17: =D14*100/(H14-G14) | F17: %

Sheet Workflow Authentication 
B1: Workflow Authentication
A2: Workflow | B2: UC01–UC04: Register, Login, Logout, Forgot/Reset Password | R2: Passed
A3: Test requirement | B3: Đăng nhập tài khoản, tạo tài khoản và reset mật khẩu | R3: Failed
A4: Number of TCs | B4: =COUNTA(A12:A999) | R4: Pending
A5: Testing Round | B5: Passed | C5: Failed | D5: Pending | E5: N/A | R5: N/A
A6: Round 1 | B6: =COUNTIF($F10:$F997,B5) | C6: =COUNTIF($F10:$F997,C5) | D6: =COUNTIF($F10:$F997,D5) | E6: =COUNTIF($F10:$F997,E5)
A7: Round 2 | B7: =COUNTIF($F10:$F997,B5) | C7: =COUNTIF($F10:$F997,C5) | D7: =COUNTIF($F10:$F997,D5) | E7: =COUNTIF($F10:$F997,E5)
A8: Round 3 | B8: =COUNTIF($F10:$F997,B5) | C8: =COUNTIF($F10:$F997,C5) | D8: =COUNTIF($F10:$F997,D5) | E8: =COUNTIF($F10:$F997,E5)
A10: Scenario A — Login with valid credentials
A11: AUTH-01 | B11: Login with valid Staff (Manager) | C11: 1. Navigate to /login 2. Enter valid Manager username+password 3. Click Login | D11: JWT token issued. Redirected to /dashboard. Manager sidebar rendered. | E11: Active Manager account in DB | F11: Passed | G11: 07/04/2026 | H11: Team | I11: Passed | J11: 07/04/2026 | K11: Team | L11: Passed | M11: 07/04/2026 | N11: Team
A12: AUTH-02 | B12: Login with valid Resident account | C12: 1. Navigate to /login 2. Enter valid Resident credentials 3. Click Login | D12: JWT token issued. Redirected to /resident. Resident portal displayed. | E12: Active Resident account in DB | F12: Passed | G12: 07/04/2026 | H12: Team | I12: Passed | J12: 07/04/2026 | K12: Team | L12: Passed | M12: 07/04/2026 | N12: Team
A13: AUTH-03 | B13: Login with Admin role — all menus visible | C13: 1. Login as Admin 2. Check sidebar | D13: All staff menu items visible (Dashboard, Staff, Resident, Apartments, Invoices, Vehicles, Notifications, Service Requests). | E13: Active Admin account | F13: Passed | G13: 07/04/2026 | H13: Team | I13: Passed | J13: 07/04/2026 | K13: Team | L13: Passed | M13: 07/04/2026 | N13: Team
A14: Scenario B — Login failures
A15: AUTH-04 | B15: Wrong password | C15: 1. Enter valid username with incorrect password 2. Click Login | D15: Login fails. Error message shown. No JWT issued. | E15: Valid account exists | F15: Passed | G15: 07/04/2026 | H15: Team | I15: Passed | J15: 07/04/2026 | K15: Team | L15: Passed | M15: 07/04/2026 | N15: Team
A16: AUTH-05 | B16: Non-existent username | C16: 1. Enter username that does not exist 2. Click Login | D16: Login fails. "Invalid credentials" message shown. | E16: Username not in DB | F16: Passed | G16: 07/04/2026 | H16: Team | I16: Passed | J16: 07/04/2026 | K16: Team | L16: Passed | M16: 07/04/2026 | N16: Team
A17: AUTH-06 | B17: PENDING resident cannot login | C17: 1. Enter credentials of PENDING resident 2. Click Login | D17: Login fails. Message indicates account pending approval. | E17: PENDING resident account | F17: Passed | G17: 07/04/2026 | H17: Team | I17: Passed | J17: 07/04/2026 | K17: Team | L17: Passed | M17: 07/04/2026 | N17: Team
A18: AUTH-07 | B18: INACTIVE resident cannot login | C18: 1. Enter credentials of INACTIVE resident 2. Click Login | D18: Login fails with 403 error. | E18: INACTIVE resident account | F18: Passed | G18: 07/04/2026 | H18: Team | I18: Passed | J18: 07/04/2026 | K18: Team | L18: Passed | M18: 07/04/2026 | N18: Team
A19: Scenario C — Register new resident (UC01)
A20: AUTH-08 | B20: Successful resident registration | C20: 1. Navigate to /register 2. Fill all required fields 3. Click Register | D20: Account created (PENDING). Success message. Visible in staff Resident Management. | E20: No existing account with same username/phone | F20: Passed | G20: 07/04/2026 | H20: Team | I20: Passed | J20: 07/04/2026 | K20: Team | L20: Passed | M20: 07/04/2026 | N20: Team
A21: AUTH-09 | B21: Register with duplicate username | C21: 1. Navigate to /register 2. Enter existing username 3. Register | D21: Error: duplicate username. Account not created. | E21: Account with same username exists | F21: Passed | G21: 07/04/2026 | H21: Team | I21: Passed | J21: 07/04/2026 | K21: Team | L21: Passed | M21: 07/04/2026 | N21: Team
A22: AUTH-10 | B22: Register with missing required fields | C22: 1. Leave title/phone/password blank 2. Click Register | D22: Validation errors shown per field. Not submitted. | E22: None | F22: Passed | G22: 07/04/2026 | H22: Team | I22: Passed | J22: 07/04/2026 | K22: Team | L22: Passed | M22: 07/04/2026 | N22: Team
A23: Scenario D — Forgot/Reset Password (UC04)
A24: AUTH-11 | B24: Request password reset with valid email | C24: 1. Navigate to /forgot-password 2. Enter registered email 3. Submit | D24: Success message. Reset email sent with valid link. | E24: Account with that email exists | F24: Passed | G24: 07/04/2026 | H24: Team | I24: Passed | J24: 07/04/2026 | K24: Team | L24: Passed | M24: 07/04/2026 | N24: Team
A25: AUTH-12 | B25: Reset password with valid token | C25: 1. Click link in reset email 2. Enter new password 3. Submit | D25: Password updated. Can login with new password. | E25: Valid (non-expired) reset token | F25: Passed | G25: 07/04/2026 | H25: Team | I25: Passed | J25: 07/04/2026 | K25: Team | L25: Passed | M25: 07/04/2026 | N25: Team
A26: AUTH-13 | B26: Reset password with expired token (>15 min) | C26: 1. Wait >15 minutes 2. Click old reset link 3. Try to submit | D26: Error: token expired. Prompted to request new link. | E26: Expired reset token | F26: Passed | G26: 07/04/2026 | H26: Team | I26: Passed | J26: 07/04/2026 | K26: Team | L26: Passed | M26: 07/04/2026 | N26: Team
A27: AUTH-14 | B27: Logout clears session | C27: 1. Login as any user 2. Click Logout 3. Try to access /dashboard | D27: Token cleared. Redirected to /login. | E27: Active login session | F27: Passed | G27: 07/04/2026 | H27: Team | I27: Passed | J27: 07/04/2026 | K27: Team | L27: Passed | M27: 07/04/2026 | N27: Team

Sheet Workflow Dashboard
B1: Workflow Dashboard
A2: Workflow | B2: UC05–UC08: Profile Management + Dashboard Overview | R2: Passed
A3: Test requirement | B3: Thấy được dashboard tổng ở cả staff và resident | R3: Failed
A4: Number of TCs | B4: =COUNTA(A12:A994) | R4: Pending
A5: Testing Round | B5: Passed | C5: Failed | D5: Pending | E5: N/A | R5: N/A
A6: Round 1 | B6: =COUNTIF($F10:$F992,B5) | C6: =COUNTIF($F10:$F992,C5) | D6: =COUNTIF($F10:$F992,D5) | E6: =COUNTIF($F10:$F992,E5)
A7: Round 2 | B7: =COUNTIF($F10:$F992,B5) | C7: =COUNTIF($F10:$F992,C5) | D7: =COUNTIF($F10:$F992,D5) | E7: =COUNTIF($F10:$F992,E5)
A8: Round 3 | B8: =COUNTIF($F10:$F992,B5) | C8: =COUNTIF($F10:$F992,C5) | D8: =COUNTIF($F10:$F992,D5) | E8: =COUNTIF($F10:$F992,E5)
A10: Scenario A — Staff Dashboard Overview (UC08)
A11: DASH-01 | B11: Admin sees all stats on dashboard | C11: 1. Login as Admin 2. Navigate to /dashboard | D11: Dashboard shows: total apartments, total residents, total staff, invoices by status (UNPAID/PAID/OVERDUE), pending service requests. | E11: Admin account + data in DB | F11: Passed | G11: 07/04/2026 | H11: Team | I11: Passed | J11: 07/04/2026 | K11: Team | L11: Passed | M11: 07/04/2026 | N11: Team
A12: DASH-02 | B12: Manager dashboard matches Admin view | C12: 1. Login as Manager 2. Navigate to /dashboard | D12: Same stats visible. Manager sidebar shown. | E12: Manager account | F12: Passed | G12: 07/04/2026 | H12: Team | I12: Passed | J12: 07/04/2026 | K12: Team | L12: Passed | M12: 07/04/2026 | N12: Team
A13: DASH-03 | B13: Accountant accesses dashboard | C13: 1. Login as Accountant 2. Navigate to /dashboard | D13: Dashboard visible. Sidebar shows only: Dashboard, Buildings, Invoices, Notifications. | E13: Accountant account | F13: Passed | G13: 07/04/2026 | H13: Team | I13: Passed | J13: 07/04/2026 | K13: Team | L13: Passed | M13: 07/04/2026 | N13: Team
A14: DASH-04 | B14: Technician access is restricted | C14: 1. Login as Technician 2. Navigate to /dashboard/apartments (forbidden) | D14: Redirected to /dashboard/service-requests (Technician default). Cannot access apartments page. | E14: Technician account | F14: Passed | G14: 07/04/2026 | H14: Team | I14: Passed | J14: 07/04/2026 | K14: Team | L14: Passed | M14: 07/04/2026 | N14: Team
A15: Scenario B — Resident Home Dashboard
A16: DASH-05 | B16: Resident home shows correct stats | C16: 1. Login as Active Resident with apartment 2. Navigate to /resident | D16: Shows: unpaid invoice count, pending request count, vehicle count, unread notification badge. | E16: Active resident with apartment, invoices, requests | F16: Passed | G16: 07/04/2026 | H16: Team | I16: Passed | J16: 07/04/2026 | K16: Team | L16: Passed | M16: 07/04/2026 | N16: Team
A17: DASH-06 | B17: Resident without apartment sees empty state | C17: 1. Login as Resident not assigned to apartment 2. Navigate to /resident/apartment | D17: Message: "Chưa được gán căn hộ". No apartment info shown. | E17: Active resident with NO apartment | F17: Passed | G17: 07/04/2026 | H17: Team | I17: Passed | J17: 07/04/2026 | K17: Team | L17: Passed | M17: 07/04/2026 | N17: Team
A18: Scenario C — Profile Management (UC05, UC06, UC07)
A19: DASH-07 | B19: View profile — all fields visible | C19: 1. Login as any user 2. Navigate to /profile | D19: Profile shows: full name, email, phone, gender, DOB, role/type, last login. | E19: Active account | F19: Passed | G19: 07/04/2026 | H19: Team | I19: Passed | J19: 07/04/2026 | K19: Team | L19: Passed | M19: 07/04/2026 | N19: Team
A20: DASH-08 | B20: Update profile — change phone number | C20: 1. Navigate to /profile 2. Edit phone to new value 3. Save | D20: Profile updated. New phone shown immediately. | E20: Active account | F20: Passed | G20: 07/04/2026 | H20: Team | I20: Passed | J20: 07/04/2026 | K20: Team | L20: Passed | M20: 07/04/2026 | N20: Team
A21: DASH-09 | B21: Change password — correct current password | C21: 1. Navigate to /profile password section 2. Enter correct current password + new password 3. Save | D21: Password changed. Can login with new password. | E21: Active account | F21: Passed | G21: 07/04/2026 | H21: Team | I21: Passed | J21: 07/04/2026 | K21: Team | L21: Passed | M21: 07/04/2026 | N21: Team
A22: DASH-10 | B22: Change password — wrong current password | C22: 1. Enter incorrect current password 2. Submit | D22: Error: "Current password incorrect". Password unchanged. | E22: Active account | F22: Passed | G22: 07/04/2026 | H22: Team | I22: Passed | J22: 07/04/2026 | K22: Team | L22: Passed | M22: 07/04/2026 | N22: Team

Sheet Workflow Management
B1: Workflow Management
A2: Workflow | B2: UC09–UC12: Staff/Resident/Building/Fee Template Management | R2: Passed
A3: Test requirement | B3: <Brief description about requirements which are tested in this sheet> | R3: Failed
A4: Number of TCs | B4: =COUNTA(A12:A998) | R4: Pending
A5: Testing Round | B5: Passed | C5: Failed | D5: Pending | E5: N/A | R5: N/A
A6: Round 1 | B6: =COUNTIF($F10:$F996,B5) | C6: =COUNTIF($F10:$F996,C5) | D6: =COUNTIF($F10:$F996,D5) | E6: =COUNTIF($F10:$F996,E5)
A7: Round 2 | B7: =COUNTIF($F10:$F996,B5) | C7: =COUNTIF($F10:$F996,C5) | D7: =COUNTIF($F10:$F996,D5) | E7: =COUNTIF($F10:$F996,E5)
A8: Round 3 | B8: =COUNTIF($F10:$F996,B5) | C8: =COUNTIF($F10:$F996,C5) | D8: =COUNTIF($F10:$F996,D5) | E8: =COUNTIF($F10:$F996,E5)
A10: Scenario A — Staff Account Management (UC09)
A11: MGMT-01 | B11: Create new staff account | C11: 1. Login as Admin 2. /dashboard/staff → Add Staff 3. Fill username, fullName, phone, role=ACCOUNTANT 4. Save | D11: Staff account created. Appears in staff list. Can login. | E11: Admin account | F11: Passed | G11: 07/04/2026 | H11: Team | I11: Passed | J11: 07/04/2026 | K11: Team | L11: Passed | M11: 07/04/2026 | N11: Team
A12: MGMT-02 | B12: Edit staff — update phone and position | C12: 1. Find staff 2. Click Edit 3. Change phone + position 4. Save | D12: Staff info updated. | E12: Existing staff account | F12: Passed | G12: 07/04/2026 | H12: Team | I12: Passed | J12: 07/04/2026 | K12: Team | L12: Passed | M12: 07/04/2026 | N12: Team
A13: MGMT-03 | B13: Deactivate staff account | C13: 1. Find active staff 2. Click Deactivate 3. Confirm | D13: Status = RESIGNED. Staff cannot login. | E13: Active non-Admin staff | F13: Passed | G13: 07/04/2026 | H13: Team | I13: Passed | J13: 07/04/2026 | K13: Team | L13: Passed | M13: 07/04/2026 | N13: Team
A14: Scenario B — Resident Account Management (UC10)
A15: MGMT-04 | B15: Approve PENDING resident | C15: 1. /dashboard/resident → find PENDING resident 2. Click Approve | D15: Resident status = ACTIVE. Can now login. | E15: PENDING resident exists | F15: Passed | G15: 07/04/2026 | H15: Team | I15: Passed | J15: 07/04/2026 | K15: Team | L15: Passed | M15: 07/04/2026 | N15: Team
A16: MGMT-05 | B16: Assign resident to apartment | C16: 1. Open resident detail 2. Assign to EMPTY apartment | D16: Resident assigned to apartment. Apartment status = OCCUPIED. | E16: Active unassigned resident + EMPTY apartment | F16: Passed | G16: 07/04/2026 | H16: Team | I16: Passed | J16: 07/04/2026 | K16: Team | L16: Passed | M16: 07/04/2026 | N16: Team
A17: MGMT-06 | B17: Deactivate resident | C17: 1. Find active resident 2. Click Deactivate | D17: Status = INACTIVE. Cannot login. | E17: Active resident | F17: Passed | G17: 07/04/2026 | H17: Team | I17: Passed | J17: 07/04/2026 | K17: Team | L17: Passed | M17: 07/04/2026 | N17: Team
A18: Scenario C — Building & Apartment Management (UC11)
A19: MGMT-07 | B19: Create new building | C19: 1. /dashboard/apartments → Tòa nhà tab → Add Building 2. Fill name, address 3. Save | D19: Building created. Appears in all building dropdowns. | E19: Admin/Manager account | F19: Passed | G19: 07/04/2026 | H19: Team | I19: Passed | J19: 07/04/2026 | K19: Team | L19: Passed | M19: 07/04/2026 | N19: Team
A20: MGMT-08 | B20: Create new apartment | C20: 1. Apartments tab → Add Apartment 2. Select building, enter number/floor/area 3. Save | D20: Apartment created with status=EMPTY. | E20: Building exists | F20: Passed | G20: 07/04/2026 | H20: Team | I20: Passed | J20: 07/04/2026 | K20: Team | L20: Passed | M20: 07/04/2026 | N20: Team
A21: MGMT-09 | B21: Edit apartment status to MAINTENANCE | C21: 1. Find apartment 2. Edit → status=MAINTENANCE 3. Save | D21: Apartment status updated. Shown as MAINTENANCE in list. | E21: Existing apartment | F21: Passed | G21: 07/04/2026 | H21: Team | I21: Passed | J21: 07/04/2026 | K21: Team | L21: Passed | M21: 07/04/2026 | N21: Team
A22: MGMT-10 | B22: Duplicate apartment number in same building rejected | C22: 1. Try to create apartment with same number as existing one in same building | D22: Error message. Apartment not created. | E22: Apartment with same number/building exists | F22: Passed | G22: 07/04/2026 | H22: Team | I22: Passed | J22: 07/04/2026 | K22: Team | L22: Passed | M22: 07/04/2026 | N22: Team
A23: MGMT-11 | B23: View apartment detail with fee charges | C23: 1. Click eye icon on apartment 2. View Chi tiết modal | D23: Modal shows apartment info + activeFees table + totalEstimatedMonthly. | E23: Apartment with active fee templates | F23: Passed | G23: 07/04/2026 | H23: Team | I23: Passed | J23: 07/04/2026 | K23: Team | L23: Passed | M23: 07/04/2026 | N23: Team
A24: Scenario D — Fee Template Management (UC12)
A25: MGMT-12 | B25: Create SERVICE/PER_M2 fee template | C25: 1. Fee Templates tab → select building → Add Fee Template 2. type=SERVICE, unit=PER_M2, amount=7000 3. Save | D25: Fee template ACTIVE. Estimated cost shown in apartment list. | E25: Building with apartments | F25: Passed | G25: 07/04/2026 | H25: Team | I25: Passed | J25: 07/04/2026 | K25: Team | L25: Passed | M25: 07/04/2026 | N25: Team
A26: MGMT-13 | B26: Create PARKING/FIXED fee | C26: 1. Add Fee Template 2. type=PARKING, name="Phí gửi xe máy", unit=FIXED, amount=100000 3. Save | D26: Parking fee created. Applies to apartments with approved motorbikes. | E26: Building exists | F26: Passed | G26: 07/04/2026 | H26: Team | I26: Passed | J26: 07/04/2026 | K26: Team | L26: Passed | M26: 07/04/2026 | N26: Team
A27: MGMT-14 | B27: Edit fee template amount | C27: 1. Find fee template 2. Click Edit 3. Change amount 4. Save 5. Verify all fields pre-filled correctly | D27: Form pre-fills all existing values correctly (name, type, unit, amount, dates, minArea/maxArea). Update saved. | E27: Existing fee template | F27: Passed | G27: 07/04/2026 | H27: Team | I27: Passed | J27: 07/04/2026 | K27: Team | L27: Passed | M27: 07/04/2026 | N27: Team
A28: MGMT-15 | B28: Deactivate fee template | C28: 1. Find active fee 2. Click ban icon 3. Confirm | D28: Status = INACTIVE. No longer included in invoice calculations. | E28: Active fee template | F28: Passed | G28: 07/04/2026 | H28: Team | I28: Passed | J28: 07/04/2026 | K28: Team | L28: Passed | M28: 07/04/2026 | N28: Team
A29: MGMT-16 | B29: Gợi ý theo NĐ — use decree suggestion | C29: 1. Click "Gợi ý theo NĐ" 2. Review QĐ 33/2025 ranges 3. Click "Dùng" for elevator fee | D29: Fee form pre-filled with correct name/type/unit/amount. Can save directly. | E29: Admin/Manager logged in | F29: Passed | G29: 07/04/2026 | H29: Team | I29: Passed | J29: 07/04/2026 | K29: Team | L29: Passed | M29: 07/04/2026 | N29: Team

Sheet Workflow Invoice
B1: Workflow Invoice
A2: Workflow | B2: UC13–UC17: Create Invoice, View, Update Status, Pay via MoMo | R2: Passed
A3: Test requirement | B3: <Brief description about requirements which are tested in this sheet> | R3: Failed
A4: Number of TCs | B4: =COUNTA(A12:A998) | R4: Pending
A5: Testing Round | B5: Passed | C5: Failed | D5: Pending | E5: N/A | R5: N/A
A6: Round 1 | B6: =COUNTIF($F10:$F996,B5) | C6: =COUNTIF($F10:$F996,C5) | D6: =COUNTIF($F10:$F996,D5) | E6: =COUNTIF($F10:$F996,E5)
A7: Round 2 | B7: =COUNTIF($F10:$F996,B5) | C7: =COUNTIF($F10:$F996,C5) | D7: =COUNTIF($F10:$F996,D5) | E7: =COUNTIF($F10:$F996,E5)
A8: Round 3 | B8: =COUNTIF($F10:$F996,B5) | C8: =COUNTIF($F10:$F996,C5) | D8: =COUNTIF($F10:$F996,D5) | E8: =COUNTIF($F10:$F996,E5)
A10: Scenario A — Invoice Creation (UC13)
A11: INV-01 | B11: Create invoice — auto-calculate all fee types | C11: 1. Login as Accountant 2. /dashboard/invoices → Create Invoice 3. Select building + apartment + month=4 + year=2026 + dueDate 4. Submit | D11: Invoice created (UNPAID). Line items: SERVICE fees (rate×area), PARKING fees (rate×vehicle count). Total = sum of lines. | E11: Apartment with active fee templates + approved vehicles | F11: Passed | G11: 07/04/2026 | H11: Team | I11: Passed | J11: 07/04/2026 | K11: Team | L11: Passed | M11: 07/04/2026 | N11: Team
A12: INV-02 | B12: Create invoices for entire building | C12: 1. Create Invoice 2. Select building only (no specific apartment) 3. Submit | D12: Invoices created for all apartments in building. | E12: Building with multiple apartments + fee templates | F12: Passed | G12: 07/04/2026 | H12: Team | I12: Passed | J12: 07/04/2026 | K12: Team | L12: Passed | M12: 07/04/2026 | N12: Team
A13: INV-03 | B13: Duplicate invoice creation rejected | C13: 1. Try to create invoice for same apartment/month/year twice | D13: Error: "Hóa đơn đã tồn tại". Second invoice NOT created. | E13: Invoice for that apt/month/year already exists | F13: Passed | G13: 07/04/2026 | H13: Team | I13: Passed | J13: 07/04/2026 | K13: Team | L13: Passed | M13: 07/04/2026 | N13: Team
A14: INV-04 | B14: Invoice with PER_M2 area-range filtering | C14: 1. Create fee template with minArea=50, maxArea=100 2. Create invoice for 120m² apartment | D14: Fee NOT applied to 120m² apartment (outside range). Invoice has 0 for that fee line. | E14: Fee template with area range; apartment outside range | F14: Passed | G14: 07/04/2026 | H14: Team | I14: Passed | J14: 07/04/2026 | K14: Team | L14: Passed | M14: 07/04/2026 | N14: Team
A15: Scenario B — View & Search Invoices (UC14)
A16: INV-05 | B16: View invoice list — no filters | C16: 1. /dashboard/invoices (load all) | D16: All invoices shown. Columns: apartment, month/year, total, status, due date. | E16: At least 1 invoice in DB | F16: Passed | G16: 07/04/2026 | H16: Team | I16: Passed | J16: 07/04/2026 | K16: Team | L16: Passed | M16: 07/04/2026 | N16: Team
A17: INV-06 | B17: Filter by building + status=UNPAID | C17: 1. Select building 2. Select status=UNPAID 3. Search | D17: Only UNPAID invoices for selected building shown. | E17: Invoices with different statuses | F17: Passed | G17: 07/04/2026 | H17: Team | I17: Passed | J17: 07/04/2026 | K17: Team | L17: Passed | M17: 07/04/2026 | N17: Team
A18: INV-07 | B18: View invoice fee detail breakdown | C18: 1. Click view icon on invoice | D18: Detail shows: fee name, type, unit price, quantity, subtotal per line. Total = sum. | E18: Invoice with fee detail records | F18: Passed | G18: 07/04/2026 | H18: Team | I18: Passed | J18: 07/04/2026 | K18: Team | L18: Passed | M18: 07/04/2026 | N18: Team
A19: Scenario C — Update Invoice Status (UC15)
A20: INV-08 | B20: Manually mark invoice as PAID (cash) | C20: 1. Find UNPAID invoice 2. Update Status → PAID 3. Confirm | D20: Invoice = PAID. paid_at timestamp set. | E20: UNPAID invoice; Admin/Manager logged in | F20: Passed | G20: 07/04/2026 | H20: Team | I20: Passed | J20: 07/04/2026 | K20: Team | L20: Passed | M20: 07/04/2026 | N20: Team
A21: INV-09 | B21: OVERDUE invoice after scheduler runs | C21: 1. Create UNPAID invoice with due_date = yesterday 2. Scheduler runs (or manually trigger) 3. Check invoice status | D21: Invoice = OVERDUE. Resident received notification + email. | E21: UNPAID invoice with past due_date | F21: Passed | G21: 07/04/2026 | H21: Team | I21: Passed | J21: 07/04/2026 | K21: Team | L21: Passed | M21: 07/04/2026 | N21: Team
A22: Scenario D — Resident Invoice View (UC16)
A23: INV-10 | B23: Resident views own invoices | C23: 1. Login as Resident 2. /resident/invoices | D23: Only invoices for this resident's apartment shown. Fee breakdown per invoice visible. | E23: Active resident with apartment + invoices | F23: Passed | G23: 07/04/2026 | H23: Team | I23: Passed | J23: 07/04/2026 | K23: Team | L23: Passed | M23: 07/04/2026 | N23: Team
A24: INV-11 | B24: Resident filters by month/year | C24: 1. Select filterType=month, month=4, year=2026 | D24: Only April 2026 invoice shown (or empty). | E24: Resident with multiple invoices | F24: Passed | G24: 07/04/2026 | H24: Team | I24: Passed | J24: 07/04/2026 | K24: Team | L24: Passed | M24: 07/04/2026 | N24: Team
A25: Scenario E — MoMo Payment (UC17)
A26: INV-12 | B26: Initiate MoMo payment | C26: 1. Login as Resident 2. /resident/invoices → click "Thanh toán qua MoMo" 3. Observe redirect | D26: System creates payment session. Resident redirected to MoMo URL/deeplink. | E26: UNPAID invoice; MoMo sandbox credentials configured | F26: Passed | G26: 07/04/2026 | H26: Team | I26: Passed | J26: 07/04/2026 | K26: Team | L26: Passed | M26: 07/04/2026 | N26: Team
A27: INV-13 | B27: MoMo IPN callback marks invoice PAID | C27: 1. Complete payment in MoMo sandbox 2. MoMo sends IPN to /api/momo/ipn 3. Refresh invoice | D27: Invoice = PAID. paid_at set. Payments record created with momo_trans_id. | E27: Completed MoMo payment + sandbox IPN configured | F27: Passed | G27: 07/04/2026 | H27: Team | I27: Passed | J27: 07/04/2026 | K27: Team | L27: Passed | M27: 07/04/2026 | N27: Team
A28: INV-14 | B28: Invalid MoMo IPN signature rejected | C28: 1. Send POST to /api/momo/ipn with invalid signature 2. Check invoice | D28: IPN rejected. Invoice status unchanged. | E28: UNPAID invoice | F28: Passed | G28: 07/04/2026 | H28: Team | I28: Passed | J28: 07/04/2026 | K28: Team | L28: Passed | M28: 07/04/2026 | N28: Team

Sheet Workflow Request
B1: Workflow Request
A2: Workflow | B2: UC18–UC29: Service Requests, Vehicles, Notifications, Apartment Info | R2: Passed
A3: Test requirement | B3: <Brief description about requirements which are tested in this sheet> | R3: Failed
A4: Number of TCs | B4: =COUNTA(A12:A998) | R4: Pending
A5: Testing Round | B5: Passed | C5: Failed | D5: Pending | E5: N/A | R5: N/A
A6: Round 1 | B6: =COUNTIF($F10:$F996,B5) | C6: =COUNTIF($F10:$F996,C5) | D6: =COUNTIF($F10:$F996,D5) | E6: =COUNTIF($F10:$F996,E5)
A7: Round 2 | B7: =COUNTIF($F10:$F996,B5) | C7: =COUNTIF($F10:$F996,C5) | D7: =COUNTIF($F10:$F996,D5) | E7: =COUNTIF($F10:$F996,E5)
A8: Round 3 | B8: =COUNTIF($F10:$F996,B5) | C8: =COUNTIF($F10:$F996,C5) | D8: =COUNTIF($F10:$F996,D5) | E8: =COUNTIF($F10:$F996,E5)
A10: Scenario A — Submit Service Request (UC18)
A11: REQ-01 | B11: Resident submits request | C11: 1. Login as Resident 2. /resident/requests → Submit Request 3. Fill title, description, category=ELECTRIC, priority=MEDIUM 4. Submit | D11: Request created (PENDING). Visible in resident list and staff list. | E11: Active resident with apartment | F11: Passed | G11: 07/04/2026 | H11: Team | I11: Passed | J11: 07/04/2026 | K11: Team | L11: Passed | M11: 07/04/2026 | N11: Team
A12: REQ-02 | B12: Submit with blank required fields | C12: 1. Leave title or description blank 2. Submit | D12: Validation error. Request not created. | E12: Active resident | F12: Passed | G12: 07/04/2026 | H12: Team | I12: Passed | J12: 07/04/2026 | K12: Team | L12: Passed | M12: 07/04/2026 | N12: Team
A13: Scenario B — Staff Manages Requests (UC22)
A14: REQ-03 | B14: Manager assigns request to Technician | C14: 1. Login as Manager 2. /dashboard/service-requests 3. Find PENDING request → Assign → select Technician | D14: Status = IN_PROGRESS. Technician name shown. Resident notified. | E14: PENDING request + active Technician | F14: Passed | G14: 07/04/2026 | H14: Team | I14: Passed | J14: 07/04/2026 | K14: Team | L14: Passed | M14: 07/04/2026 | N14: Team
A15: REQ-04 | B15: Technician marks request DONE with image | C15: 1. Login as Technician 2. Find assigned IN_PROGRESS request 3. Mark Done → add note + upload image | D15: Status = DONE. Image and note saved. Resident notified. | E15: IN_PROGRESS request assigned to this Technician | F15: Passed | G15: 07/04/2026 | H15: Team | I15: Passed | J15: 07/04/2026 | K15: Team | L15: Passed | M15: 07/04/2026 | N15: Team
A16: REQ-05 | B16: Staff rejects request with reason | C16: 1. Login as Manager 2. Find PENDING request → Reject → enter reason | D16: Status = REJECTED. Reason saved. Resident notified. | E16: PENDING request | F16: Passed | G16: 07/04/2026 | H16: Team | I16: Passed | J16: 07/04/2026 | K16: Team | L16: Passed | M16: 07/04/2026 | N16: Team
A17: REQ-06 | B17: Technician only sees own assigned requests | C17: 1. Login as Technician 2. View service request list | D17: Only requests assigned to THIS Technician visible. | E17: Requests assigned to multiple technicians | F17: Passed | G17: 07/04/2026 | H17: Team | I17: Passed | J17: 07/04/2026 | K17: Team | L17: Passed | M17: 07/04/2026 | N17: Team
A18: Scenario C — Resident Actions on Requests (UC19, UC20, UC21)
A19: REQ-07 | B19: Resident cancels PENDING request | C19: 1. Login as Resident 2. /resident/requests → find PENDING request 3. Click Cancel → Confirm | D19: Status = CANCELLED. Cannot be un-cancelled. | E19: PENDING request by this resident | F19: Passed | G19: 07/04/2026 | H19: Team | I19: Passed | J19: 07/04/2026 | K19: Team | L19: Passed | M19: 07/04/2026 | N19: Team
A20: REQ-08 | B20: Cannot cancel IN_PROGRESS request | C20: 1. Try to cancel IN_PROGRESS request | D20: Error: "Chỉ có thể hủy yêu cầu đang ở trạng thái PENDING". Cancel blocked. | E20: IN_PROGRESS request | F20: Passed | G20: 07/04/2026 | H20: Team | I20: Passed | J20: 07/04/2026 | K20: Team | L20: Passed | M20: 07/04/2026 | N20: Team
A21: REQ-09 | B21: Resident confirms DONE request | C21: 1. Find DONE request 2. Click Confirm Completion | D21: residentConfirmed = true. confirmedAt timestamp set. | E21: DONE (unconfirmed) request | F21: Passed | G21: 07/04/2026 | H21: Team | I21: Passed | J21: 07/04/2026 | K21: Team | L21: Passed | M21: 07/04/2026 | N21: Team
A22: REQ-10 | B22: Resident views DONE request detail with image | C22: 1. Click on DONE request to view detail | D22: Detail shows title, description, status, note, completion image, assigned staff name. | E22: DONE request with image uploaded | F22: Passed | G22: 07/04/2026 | H22: Team | I22: Passed | J22: 07/04/2026 | K22: Team | L22: Passed | M22: 07/04/2026 | N22: Team
A23: Scenario D — Vehicle Registration (UC23–UC25)
A24: VEH-01 | B24: Resident registers vehicle | C24: 1. Login as Resident 2. /resident/vehicles → register 3. Fill type=MOTORBIKE, licensePlate, brand, durationType=MONTHLY | D24: Vehicle created (pendingStatus=PENDING). Visible in resident vehicle list. | E24: Active resident with apartment | F24: Passed | G24: 07/04/2026 | H24: Team | I24: Passed | J24: 07/04/2026 | K24: Team | L24: Passed | M24: 07/04/2026 | N24: Team
A25: VEH-02 | B25: Staff approves vehicle | C25: 1. Login as Receptionist 2. /dashboard/vehicles → find PENDING vehicle → Approve | D25: pendingStatus = APPROVED. expiredAt calculated (+1 month for MONTHLY). Resident notified. | E25: PENDING vehicle registration | F25: Passed | G25: 07/04/2026 | H25: Team | I25: Passed | J25: 07/04/2026 | K25: Team | L25: Passed | M25: 07/04/2026 | N25: Team
A26: VEH-03 | B26: Staff rejects vehicle with reason | C26: 1. Find PENDING vehicle → Reject → enter reason | D26: pendingStatus = REJECTED. Reason saved. Resident notified. | E26: PENDING vehicle registration | F26: Passed | G26: 07/04/2026 | H26: Team | I26: Passed | J26: 07/04/2026 | K26: Team | L26: Passed | M26: 07/04/2026 | N26: Team
A27: VEH-04 | B27: Duplicate license plate rejected | C27: 1. Try to register vehicle with license plate already in DB | D27: Error: duplicate license plate. Vehicle not created. | E27: Vehicle with same license plate exists | F27: Passed | G27: 07/04/2026 | H27: Team | I27: Passed | J27: 07/04/2026 | K27: Team | L27: Passed | M27: 07/04/2026 | N27: Team
A28: Scenario E — Notifications (UC27–UC28)
A29: NOTIF-01 | B29: Staff broadcasts to entire building | C29: 1. Login as Manager 2. /dashboard/notifications → type=broadcast → select building 3. Enter title + content → Send | D29: Notification sent to all ACTIVE residents in building. Unread badge incremented. | E29: Building with active residents | F29: Passed | G29: 07/04/2026 | H29: Team | I29: Passed | J29: 07/04/2026 | K29: Team | L29: Passed | M29: 07/04/2026 | N29: Team
A30: NOTIF-02 | B30: Staff sends personal notification | C30: 1. type=personal → select specific resident → send | D30: Only that resident receives notification. | E30: Active resident | F30: Passed | G30: 07/04/2026 | H30: Team | I30: Passed | J30: 07/04/2026 | K30: Team | L30: Passed | M30: 07/04/2026 | N30: Team
A31: NOTIF-03 | B31: Resident marks notification as read | C31: 1. Login as Resident 2. /resident/notifications → click on unread notification | D31: Notification is_read = true. Unread count decremented. | E31: Unread notification exists | F31: Passed | G31: 07/04/2026 | H31: Team | I31: Passed | J31: 07/04/2026 | K31: Team | L31: Passed | M31: 07/04/2026 | N31: Team
A32: NOTIF-04 | B32: Resident marks all notifications as read | C32: 1. /resident/notifications → click "Mark all as read" | D32: All notifications is_read = true. Badge shows 0. | E32: Multiple unread notifications | F32: Passed | G32: 07/04/2026 | H32: Team | I32: Passed | J32: 07/04/2026 | K32: Team | L32: Passed | M32: 07/04/2026 | N32: Team
A33: Scenario F — Access Cards + Apartment Info (UC26, UC29)
A34: NOTIF-05 | B34: Issue access card to resident | C34: 1. Login as Manager 2. Find active resident 3. Issue access card with expiry date | D34: AccessCard record (ACTIVE). Visible on resident apartment page. | E34: Active resident with apartment | F34: Passed | G34: 07/04/2026 | H34: Team | I34: Passed | J34: 07/04/2026 | K34: Team | L34: Passed | M34: 07/04/2026 | N34: Team
A35: NOTIF-06 | B35: Resident views apartment info with fee charges | C35: 1. Login as Resident 2. Navigate to /resident/apartment | D35: Page shows: apartment number, floor, area, building name/address, active fee charges table (name, type, unit, estimated amount), total estimated monthly cost, access cards, vehicles. | E35: Active resident with apartment + active fee templates + approved vehicles | F35: Passed | G35: 07/04/2026 | H35: Team | I35: Passed | J35: 07/04/2026 | K35: Team | L35: Passed | M35: 07/04/2026 | N35: Team
A36: NOTIF-07 | B36: Resident without fee templates sees empty fee section | C36: 1. Login as Resident in building with no active fee templates 2. /resident/apartment | D36: Fee section shows: "Ban quản lý chưa cấu hình mẫu phí". | E36: Active resident; building has NO active fee templates | F36: Passed | G36: 07/04/2026 | H36: Team | I36: Passed | J36: 07/04/2026 | K36: Team | L36: Passed | M36: 07/04/2026 | N36: Team
